pic2prose/__init__.py
pic2prose/structures.py
pic2prose-0.0.2.dist-info/LICENSE
pic2prose-0.0.2.dist-info/METADATA
pic2prose-0.0.2.dist-info/WHEEL
pic2prose-0.0.2.dist-info/top_level.txt
pic2prose-0.0.2.dist-info/RECORD
