Metadata-Version: 2.1
Name: pic2prose
Version: 0.0.2
Summary: Enables real-world data collection, bridges the gap between OCR and NLP, enabling you to convert text from any image to ready to use nlp data structures.
Author: Rohit Mishra
Author-email: <rohitnmishra2@gmail.com>
Keywords: python,images,text,nlp,natural,language,lexicon
Classifier: Development Status :: 1 - Planning
Classifier: Intended Audience :: Developers
Classifier: Programming Language :: Python :: 3
Classifier: Operating System :: Unix
Classifier: Operating System :: MacOS :: MacOS X
Classifier: Operating System :: Microsoft :: Windows
License-File: LICENSE
Requires-Dist: easyocr
Requires-Dist: numpy
